fastbook_questions/__init__.py
fastbook_questions/_nbdev.py
fastbook_questions/cli.py
fastbook_questions-0.0.6.dist-info/LICENSE
fastbook_questions-0.0.6.dist-info/METADATA
fastbook_questions-0.0.6.dist-info/WHEEL
fastbook_questions-0.0.6.dist-info/entry_points.txt
fastbook_questions-0.0.6.dist-info/top_level.txt
fastbook_questions-0.0.6.dist-info/RECORD
