Metadata-Version: 2.1
Name: fastbook-questions
Version: 0.0.6
Summary: Extract Questions from FastBook Notebooks
Home-page: https://github.com/wooduk/fastbook-questions/tree/master/
Author: Stephen Wood
Author-email: sgwooduk@gmail.com
License: Apache Software License 2.0
Keywords: fastai fastbook
Platform: UNKNOWN
Classifier: Development Status :: 3 - Alpha
Classifier: Intended Audience :: Developers
Classifier: License :: OSI Approved :: Apache Software License
Classifier: Natural Language :: English
Classifier: Programming Language :: Python :: 3.6
Classifier: Programming Language :: Python :: 3.7
Classifier: Programming Language :: Python :: 3.8
Requires-Python: >=3.6
Requires-Dist: nbformat (>=4.4.0)
Requires-Dist: fastscript
Requires-Dist: packaging
